mssbox/__init__.py
mssbox/connect.py
mssbox/disconnect.py
mssbox/util/__init__.py
mssbox/util/getters.py
mssbox/util/reset.py
mssbox-1.0.7.dist-info/LICENSE.txt
mssbox-1.0.7.dist-info/METADATA
mssbox-1.0.7.dist-info/WHEEL
mssbox-1.0.7.dist-info/top_level.txt
mssbox-1.0.7.dist-info/RECORD
